llama_index/llms/nvidia_tensorrt/__init__.py
llama_index/llms/nvidia_tensorrt/base.py
llama_index/llms/nvidia_tensorrt/utils.py
llama_index_llms_nvidia_tensorrt-0.4.1.dist-info/METADATA
llama_index_llms_nvidia_tensorrt-0.4.1.dist-info/WHEEL
llama_index_llms_nvidia_tensorrt-0.4.1.dist-info/licenses/LICENSE
llama_index_llms_nvidia_tensorrt-0.4.1.dist-info/RECORD
