Metadata-Version: 2.4
Name: llama-index-llms-nvidia-tensorrt
Version: 0.4.1
Summary: llama-index llms nvidia tensorrt integration
Author-email: Your Name <you@example.com>
License-Expression: MIT
License-File: LICENSE
Requires-Python: <4.0,>=3.9
Requires-Dist: llama-index-core<0.15,>=0.13.0
Requires-Dist: torch<3,>=2.1.2
Requires-Dist: transformers<5,>=4.37.0
